pyusage/__init__.py
usage/__init__.py
usage/cli.py
usage/clients.py
usage/decorators.py
usage/models.py
usage/session.py
usage/utils.py
usage/wrapped_function.py
pyusage-0.1.7.dist-info/entry_points.txt
pyusage-0.1.7.dist-info/LICENSE
pyusage-0.1.7.dist-info/WHEEL
pyusage-0.1.7.dist-info/METADATA
pyusage-0.1.7.dist-info/RECORD
