Metadata-Version: 2.1
Name: pyusage
Version: 0.1.7
Summary: 
Home-page: https://pyusage.org
License: Apache-2.0
Keywords: usage,users,monitoring,analytics
Author: PyUsage Team
Author-email: packages@pyusage.org
Maintainer: Balaji Veeramani
Maintainer-email: bveeramani@berkeley.edu
Requires-Python: >=3.7,<4.0
Classifier: Development Status :: 2 - Pre-Alpha
Classifier: Intended Audience :: Developers
Classifier: License :: OSI Approved :: Apache Software License
Classifier: Natural Language :: English
Classifier: Operating System :: MacOS :: MacOS X
Classifier: Operating System :: Microsoft :: Windows
Classifier: Operating System :: POSIX
Classifier: Operating System :: POSIX :: BSD
Classifier: Operating System :: POSIX :: Linux
Classifier: Programming Language :: Python :: 3
Classifier: Programming Language :: Python :: 3.10
Classifier: Programming Language :: Python :: 3.7
Classifier: Programming Language :: Python :: 3.8
Classifier: Programming Language :: Python :: 3.9
Classifier: Topic :: Software Development :: Libraries
Classifier: Topic :: System :: Monitoring
Requires-Dist: importlib-metadata (>=4.11.3,<5.0.0)
Requires-Dist: pydantic (>=1.9.0,<2.0.0)
Requires-Dist: requests (>=2.27.1,<3.0.0)
Requires-Dist: rich (>=12.3.0,<13.0.0)
Requires-Dist: termcolor (>=1.1.0,<2.0.0)
Project-URL: Documentation, https://docs.pyusage.org
Project-URL: Repository, https://github.com/pyusage/pyusage
